guacamole/__init__.py
guacamole/create_reference_dist.py
guacamole/guacamole.py
guacamole/library.py
guacamole_bio-1.0.1.dist-info/licenses/COPYING
guacamole_bio-1.0.1.dist-info/METADATA
guacamole_bio-1.0.1.dist-info/WHEEL
guacamole_bio-1.0.1.dist-info/entry_points.txt
guacamole_bio-1.0.1.dist-info/top_level.txt
guacamole_bio-1.0.1.dist-info/RECORD
