Metadata-Version: 2.4
Name: guacamole-bio
Version: 1.0.1
Summary: GC-aware species abundance estimation from metagenomic data.
Author-email: Laurenz Holcik <laurenz.holcik@gmail.com>
Project-URL: Homepage, https://github.com/cibiv/guacamole
Project-URL: Bug Tracker, https://github.com/cibiv/guacamole/issues
Classifier: License :: OSI Approved :: MIT License
Classifier: Programming Language :: Python :: 3
Classifier: Programming Language :: Python :: 3.10
Classifier: Programming Language :: Python :: 3.11
Classifier: Operating System :: OS Independent
Classifier: Intended Audience :: Science/Research
Classifier: Topic :: Scientific/Engineering :: Bio-Informatics
Requires-Python: >=3.10
License-File: COPYING
Requires-Dist: pandas
Requires-Dist: numpy
Requires-Dist: matplotlib
Requires-Dist: seaborn
Requires-Dist: biopython
Requires-Dist: scipy
Requires-Dist: qpsolvers[cvxopt]
Dynamic: license-file
